tablelinker/__init__.py
tablelinker/__main__.py
tablelinker/cli.py
tablelinker/convertors/basics/__init__.py
tablelinker/convertors/basics/calc_col.py
tablelinker/convertors/basics/concat_col.py
tablelinker/convertors/basics/concat_title.py
tablelinker/convertors/basics/delete_col.py
tablelinker/convertors/basics/delete_row.py
tablelinker/convertors/basics/generate_pk.py
tablelinker/convertors/basics/insert_col.py
tablelinker/convertors/basics/mapping_col.py
tablelinker/convertors/basics/move_col.py
tablelinker/convertors/basics/rename_col.py
tablelinker/convertors/basics/reorder_col.py
tablelinker/convertors/basics/round.py
tablelinker/convertors/basics/select_row.py
tablelinker/convertors/basics/split_col.py
tablelinker/convertors/basics/truncate.py
tablelinker/convertors/basics/update_col.py
tablelinker/convertors/basics/zenkaku.py
tablelinker/convertors/extras/__init__.py
tablelinker/convertors/extras/date_extract.py
tablelinker/convertors/extras/geocoder.py
tablelinker/convertors/extras/mapping_col.py
tablelinker/convertors/extras/wareki.py
tablelinker/core/__init__.py
tablelinker/core/context.py
tablelinker/core/convertors.py
tablelinker/core/csv_cleaner.py
tablelinker/core/data_type.py
tablelinker/core/date_extractor.py
tablelinker/core/fieldtypes.py
tablelinker/core/input.py
tablelinker/core/mapping.py
tablelinker/core/output.py
tablelinker/core/params.py
tablelinker/core/table.py
tablelinker/core/task.py
tablelinker/core/validators.py
tablelinker/exceptions.py
tablelinker_light-1.0.0.post2.dist-info/LICENSE.txt
tablelinker_light-1.0.0.post2.dist-info/METADATA
tablelinker_light-1.0.0.post2.dist-info/WHEEL
tablelinker_light-1.0.0.post2.dist-info/entry_points.txt
tablelinker_light-1.0.0.post2.dist-info/RECORD
