Metadata-Version: 2.1
Name: tablelinker-light
Version: 1.0.0.post2
Summary: TableLinker: CSV data processing library (light version)
Home-page: https://github.com/InfoProto/tablelinker-light
Keywords: CSV,tabular,cleansing,batch processing
Author: Takeshi Sagara
Author-email: sagara@info-proto.com
Maintainer: Takeshi Sagara
Maintainer-email: sagara@info-proto.com
Requires-Python: >=3.7,<4.0
Classifier: License :: OSI Approved :: MIT License
Classifier: Operating System :: Microsoft :: Windows :: Windows 11
Classifier: Operating System :: POSIX :: Linux
Classifier: Programming Language :: Python :: 3
Classifier: Programming Language :: Python :: 3.7
Classifier: Programming Language :: Python :: 3.8
Classifier: Programming Language :: Python :: 3.9
Classifier: Programming Language :: Python :: 3.10
Classifier: Programming Language :: Python :: 3.11
Classifier: Programming Language :: Python :: 3.12
Requires-Dist: charset-normalizer
Requires-Dist: docopt
Requires-Dist: jaconv
Requires-Dist: jageocoder (>=2.0.0)
Requires-Dist: jeraconv
Requires-Dist: munkres (>=1.1.4,<2.0.0)
Requires-Dist: openpyxl
Requires-Dist: pandas
Requires-Dist: regex (>=2023.12.25,<2024.0.0)
Requires-Dist: requests
Requires-Dist: xlrd
Project-URL: Documentation, https://tablelinker-light.readthedocs.io/
Project-URL: Repository, https://github.com/InfoProto/tablelinker-light
